[{"Year":2000,"Value":-9.3,"Units":"PERCENT"},{"Year":2001,"Value":-4.7,"Units":"PERCENT"},{"Year":2002,"Value":0.0,"Units":"PERCENT"},{"Year":2003,"Value":2.5,"Units":"PERCENT"},{"Year":2004,"Value":3.5,"Units":"PERCENT"},{"Year":2005,"Value":2.8,"Units":"PERCENT"},{"Year":2006,"Value":3.8,"Units":"PERCENT"},{"Year":2007,"Value":4.6,"Units":"PERCENT"},{"Year":2008,"Value":4.5,"Units":"PERCENT"},{"Year":2009,"Value":1.2,"Units":"PERCENT"},{"Year":2010,"Value":5.3,"Units":"PERCENT"},{"Year":2011,"Value":5.3,"Units":"PERCENT"},{"Year":2012,"Value":5.5,"Units":"PERCENT"},{"Year":2013,"Value":5.0,"Units":"PERCENT"},{"Year":2014,"Value":5.9,"Units":"PERCENT"},{"Year":2015,"Value":3.4,"Units":"PERCENT"},{"Year":2016,"Value":-0.9,"Units":"PERCENT"},{"Year":2017,"Value":0.3,"Units":"PERCENT"},{"Year":2018,"Value":2.3,"Units":"PERCENT"},{"Year":2019,"Value":0.9,"Units":"PERCENT"},{"Year":2020,"Value":-0.2,"Units":"PERCENT"},{"Year":2021,"Value":1.1,"Units":"PERCENT"}]