[{"Year":2004,"Value":40,"Units":"PERCENT"},{"Year":2005,"Value":50,"Units":"PERCENT"},{"Year":2006,"Value":50,"Units":"PERCENT"},{"Year":2007,"Value":50,"Units":"PERCENT"},{"Year":2008,"Value":50,"Units":"PERCENT"},{"Year":2009,"Value":50,"Units":"PERCENT"},{"Year":2009,"Value":0,"Units":"PERCENT"},{"Year":2010,"Value":50,"Units":"PERCENT"},{"Year":2010,"Value":0,"Units":"PERCENT"},{"Year":2011,"Value":50,"Units":"PERCENT"},{"Year":2011,"Value":0,"Units":"PERCENT"},{"Year":2012,"Value":50,"Units":"PERCENT"},{"Year":2012,"Value":20,"Units":"PERCENT"},{"Year":2013,"Value":50,"Units":"PERCENT"},{"Year":2013,"Value":20,"Units":"PERCENT"},{"Year":2014,"Value":50,"Units":"PERCENT"},{"Year":2014,"Value":20,"Units":"PERCENT"},{"Year":2014,"Value":0,"Units":"PERCENT"},{"Year":2015,"Value":50,"Units":"PERCENT"},{"Year":2015,"Value":20,"Units":"PERCENT"},{"Year":2015,"Value":0,"Units":"PERCENT"},{"Year":2016,"Value":50,"Units":"PERCENT"},{"Year":2016,"Value":20,"Units":"PERCENT"},{"Year":2016,"Value":0,"Units":"PERCENT"},{"Year":2017,"Value":50,"Units":"PERCENT"},{"Year":2017,"Value":40,"Units":"PERCENT"},{"Year":2017,"Value":0,"Units":"PERCENT"},{"Year":2018,"Value":52,"Units":"PERCENT"},{"Year":2018,"Value":50,"Units":"PERCENT"},{"Year":2018,"Value":0,"Units":"PERCENT"},{"Year":2019,"Value":54,"Units":"PERCENT"},{"Year":2019,"Value":54,"Units":"PERCENT"},{"Year":2020,"Value":70,"Units":"PERCENT"},{"Year":2020,"Value":54,"Units":"PERCENT"},{"Year":2020,"Value":40,"Units":"PERCENT"}]